LICENSE
README.md
setup.py
NextBSpiders/__init__.py
NextBSpiders/items.py
NextBSpiders/middlewares.py
NextBSpiders/pipelines.py
NextBSpiders/settings.py
NextBSpiders.egg-info/PKG-INFO
NextBSpiders.egg-info/SOURCES.txt
NextBSpiders.egg-info/dependency_links.txt
NextBSpiders.egg-info/entry_points.txt
NextBSpiders.egg-info/requires.txt
NextBSpiders.egg-info/top_level.txt
NextBSpiders/cli/__init__.py
NextBSpiders/cli/generate_user_message_csv.py
NextBSpiders/cli/statics_db.py
NextBSpiders/cli/telegram_clear_dialog.py
NextBSpiders/cli/telegram_create_table.py
NextBSpiders/cli/telegram_get_dialog.py
NextBSpiders/cli/telegram_get_message.py
NextBSpiders/cli/telegram_get_user_photo.py
NextBSpiders/cli/telegram_run_spider.py
NextBSpiders/configs/__init__.py
NextBSpiders/configs/postgreconfig.py
NextBSpiders/libs/__init__.py
NextBSpiders/libs/nextb_spier_db.py
NextBSpiders/spiders/__init__.py
NextBSpiders/spiders/common/__init__.py
NextBSpiders/spiders/telegramspider/__init__.py
NextBSpiders/spiders/telegramspider/telegramAPIs.py
NextBSpiders/spiders/telegramspider/telegramScanMessages.py