Metadata-Version: 2.1
Name: NextBSpiders
Version: 1.1.0
Summary: 基于scrapy的telegram爬虫
Home-page: https://github.com/a232319779/NextBSpiders
Author: ddvv
Author-email: dadavivi512@gmail.com
License: MIT
Platform: UNKNOWN
Classifier: Programming Language :: Python :: 3
Classifier: License :: OSI Approved :: MIT License
Classifier: Operating System :: OS Independent
Requires-Python: >=3.6,<3.9
License-File: LICENSE
